mooazam/__init__.py
mooazam-0.2.dist-info/License.txt
mooazam-0.2.dist-info/METADATA
mooazam-0.2.dist-info/WHEEL
mooazam-0.2.dist-info/top_level.txt
mooazam-0.2.dist-info/RECORD
