Metadata-Version: 2.1
Name: mooazam
Version: 0.2
Summary: This is Mooazam's package
Home-page: UNKNOWN
Author: Syed Muhammad Mooazam
Author-email: muhammadmoazam29@gmail.com
License: UNKNOWN
Platform: UNKNOWN
License-File: License.txt
